README.md
brevity.py
setup.py
brevity.egg-info/PKG-INFO
brevity.egg-info/SOURCES.txt
brevity.egg-info/dependency_links.txt
brevity.egg-info/top_level.txt