Metadata-Version: 1.1
Name: brevity
Version: 0.2.17
Summary: Tweet shortening and autolinking utility
Home-page: http://indiewebcamp.com/brevity
Author: Kyle Mahan
Author-email: kyle@kylewm.com
License: UNKNOWN
Platform: UNKNOWN
Classifier: Development Status :: 4 - Beta
Classifier: Intended Audience :: Developers
Classifier: License :: CC0 1.0 Universal (CC0 1.0) Public Domain Dedication
Classifier: Natural Language :: English
Classifier: Programming Language :: Python
Classifier: Programming Language :: Python :: 3
Classifier: Topic :: Text Processing
Classifier: Topic :: Utilities
